gameon/__init__.py
gameon/icon.ico
gameon-1.1.0.dist-info/LICENCE.txt
gameon-1.1.0.dist-info/METADATA
gameon-1.1.0.dist-info/WHEEL
gameon-1.1.0.dist-info/top_level.txt
gameon-1.1.0.dist-info/RECORD
