Metadata-Version: 2.1
Name: gameon
Version: 1.1.0
Summary: A useful game engine for beginners
Author: Morris El Helou
Author-email: morriselhelou816@gmail.com
License-File: LICENCE.txt
Requires-Dist: pygame
Requires-Dist: keyboard
Requires-Dist: tymer
